LICENSE
MANIFEST.in
README.rst
requirements.txt
setup.py
tox.ini
django_okta_authentication.egg-info/PKG-INFO
django_okta_authentication.egg-info/SOURCES.txt
django_okta_authentication.egg-info/dependency_links.txt
django_okta_authentication.egg-info/requires.txt
django_okta_authentication.egg-info/top_level.txt
okta_auth/__init__.py
okta_auth/backends.py
okta_auth/cache.py
okta_auth/urls.py
okta_auth/utils.py
okta_auth/views.py