Metadata-Version: 2.1
Name: django-okta-authentication
Version: 1.2
Summary: Authenticated users using Okta
Home-page: https://github.com/jasonchrista/django-okta-auth
Author: Jason Christa
Author-email: jason@zeitcode.com
Classifier: Environment :: Web Environment
Classifier: License :: OSI Approved :: BSD License
Classifier: Framework :: Django
Classifier: Programming Language :: Python
License-File: LICENSE
